RDPTools/RDPTools.py
RDPTools/__init__.py
RDPTools/client.py
RDPTools/collapse.py
RDPTools/inflate.py
RDPTools/query.py
RiboSeq_DP_Tools-0.1.10.dist-info/LICENSE
RiboSeq_DP_Tools-0.1.10.dist-info/METADATA
RiboSeq_DP_Tools-0.1.10.dist-info/WHEEL
RiboSeq_DP_Tools-0.1.10.dist-info/entry_points.txt
RiboSeq_DP_Tools-0.1.10.dist-info/top_level.txt
RiboSeq_DP_Tools-0.1.10.dist-info/RECORD
